PyMultiverse/__init__.py
PyMultiverse-0.0.0.dist-info/LICENSE
PyMultiverse-0.0.0.dist-info/METADATA
PyMultiverse-0.0.0.dist-info/WHEEL
PyMultiverse-0.0.0.dist-info/top_level.txt
PyMultiverse-0.0.0.dist-info/RECORD
