Metadata-Version: 2.1
Name: PyMultiverse
Version: 0.0.0
Summary: Multi-framework scaffolding tool
Home-page: https://github.com/rognoni/Multiverse
Author: Davide Rognoni
License: UNKNOWN
Platform: UNKNOWN
Classifier: Programming Language :: Python :: 3
Classifier: License :: OSI Approved :: GNU Affero General Public License v3
Classifier: Operating System :: OS Independent
